ledger/__init__.py
ledger/ledger.py
ledger/nlp_parser.py
ledger/user.py
main.py
quickledger-0.1.5.dist-info/LICENSE
quickledger-0.1.5.dist-info/METADATA
quickledger-0.1.5.dist-info/WHEEL
quickledger-0.1.5.dist-info/entry_points.txt
quickledger-0.1.5.dist-info/RECORD
