Metadata-Version: 2.3
Name: quickledger
Version: 0.1.5
Summary: Smart ledger that takes care of your expenses
License: MIT
Author: Chinyere
Author-email: chinyereunamba17@gmail.com
Requires-Python: >=3.10
Classifier: License :: OSI Approved :: MIT License
Classifier: Programming Language :: Python :: 3
Classifier: Programming Language :: Python :: 3.10
Classifier: Programming Language :: Python :: 3.11
Classifier: Programming Language :: Python :: 3.12
Classifier: Programming Language :: Python :: 3.13
Requires-Dist: fastapi[standard] (>=0.116.1,<0.117.0)
Requires-Dist: pandas (>=2.3.1,<3.0.0)
Requires-Dist: pydantic (>=2.5.3,<2.6.0)
Requires-Dist: python-dotenv (>=1.1.1,<2.0.0)
Requires-Dist: typer (>=0.16.0,<0.17.0)
